i3_balance_workspace/__init__.py
i3_balance_workspace/i3_balance_workspace.py
i3_balance_workspace/utils.py
i3_balance_workspace-1.8.6.dist-info/entry_points.txt
i3_balance_workspace-1.8.6.dist-info/LICENSE
i3_balance_workspace-1.8.6.dist-info/WHEEL
i3_balance_workspace-1.8.6.dist-info/METADATA
i3_balance_workspace-1.8.6.dist-info/RECORD
