Metadata-Version: 2.1
Name: i3-balance-workspace
Version: 1.8.6
Summary: Balance windows and workspaces in i3wm
Home-page: https://github.com/atreyasha/i3-balance-workspace
License: MIT
Author: Atreya Shankar
Author-email: 35427332+atreyasha@users.noreply.github.com
Requires-Python: >=3.5
Classifier: License :: OSI Approved :: MIT License
Classifier: Programming Language :: Python :: 3
Classifier: Programming Language :: Python :: 3.10
Classifier: Programming Language :: Python :: 3.5
Classifier: Programming Language :: Python :: 3.6
Classifier: Programming Language :: Python :: 3.7
Classifier: Programming Language :: Python :: 3.8
Classifier: Programming Language :: Python :: 3.9
Requires-Dist: i3ipc (>=2.2.1)
Project-URL: Repository, https://github.com/atreyasha/i3-balance-workspace
